cryptex/__init__.py
cryptex-1.1.1.dist-info/DESCRIPTION.rst
cryptex-1.1.1.dist-info/METADATA
cryptex-1.1.1.dist-info/RECORD
cryptex-1.1.1.dist-info/WHEEL
cryptex-1.1.1.dist-info/entry_points.txt
cryptex-1.1.1.dist-info/metadata.json
cryptex-1.1.1.dist-info/top_level.txt
